{
  "title": "\"Leben in Deutschland\" পরীক্ষা: ৩১০টি প্রশ্ন বাংলায় অনূদিত",
  "description": "জার্মান নাগরিকত্ব পরীক্ষা \"Leben in Deutschland\": ১০০+ ভাষায় ৩১০টি প্রশ্ন। বাংলায় প্রস্তুতি নিন — বিনামূল্যে এবং অফলাইনে।",
  "icon_alt": "LiD Trainer অ্যাপ আইকন",
  "brand_sub": "Test Trainer",
  "lang_badge": "BN",
  "top_cta": "বিনামূল্যে ডাউনলোড করুন",
  "h1": "নাগরিকত্ব পরীক্ষা — <span class=\"accent\">আপনার মাতৃভাষায়</span>",
  "hero_sub": "\"Leben in Deutschland\" পরীক্ষার সব ৩১০টি অফিসিয়াল প্রশ্ন, বাংলায় অনূদিত। সহজে শিখুন, নিজের গতিতে, ইন্টারনেট ছাড়াই।",
  "play_small": "বিনামূল্যে",
  "play_label": "Google Play",
  "ios_small": "বিনামূল্যে",
  "ios_label": "App Store",
  "hero_note": "বিনামূল্যে · অফলাইনে চলে · ১৬টি রাজ্যের প্রশ্ন",
  "hero_img_alt": "বাংলায় অ্যাপের হোম স্ক্রিন: সব প্রশ্ন, আঞ্চলিক প্রশ্ন, প্রিয়, পরিসংখ্যান",
  "lang_h2": "জার্মান উপরে, অনুবাদ হাতের নাগালে",
  "lang_p1": "প্রতিটি প্রশ্ন জার্মানে দেখানো হয় — ঠিক আসল পরীক্ষার মতো — আর তার নিচেই বাংলা অনুবাদ। আপনি বিষয়বস্তু এবং পরীক্ষায় যে হুবহু শব্দগুলো পাবেন, দুটোই শেখেন।",
  "lang_p2": "অ্যাপটি ১০০টিরও বেশি ভাষায় অনুবাদ দেয় — গুরুত্বপূর্ণ হলো, আপনার ভাষাটি ইতিমধ্যেই এখানে আছে।",
  "demo_aria": "অনুবাদসহ নমুনা প্রশ্ন",
  "demo_t": "জার্মানিতে মানুষ প্রকাশ্যে সরকারের সমালোচনা করতে পারে কারণ …",
  "ans1": "এখানে বাকস্বাধীনতা প্রযোজ্য।",
  "ans2": "মানুষ কর দেয়।",
  "demo_caption": "৩১০টির মধ্যে প্রশ্ন ১ · এক ট্যাপেই অনুবাদ লুকান",
  "feat_h2": "প্রস্তুতির জন্য যা যা দরকার — এক অ্যাপেই",
  "feat_lede": "অ্যাপের মতোই একই কার্ড: সহজ, পরিষ্কার, বাড়তি কিছু নেই।",
  "feat1_h3": "সব ৩১০টি প্রশ্ন",
  "feat1_p": "৩০০টি সাধারণ প্রশ্ন এবং আপনার রাজ্যের জন্য ১০টি প্রশ্ন — সম্পূর্ণ অফিসিয়াল তালিকা।",
  "feat2_h3": "পরীক্ষা সিমুলেটর",
  "feat2_p": "একটি অনুশীলন পরীক্ষা: ৩৩টি প্রশ্ন এবং ৬০ মিনিট সময়সীমা — অফিসিয়াল পরীক্ষার মতোই নিয়ম।",
  "feat3_h3": "তাৎক্ষণিক প্রতিক্রিয়া",
  "feat3_p": "প্রতিটি উত্তরের পরেই দেখুন সেটি সঠিক না ভুল — শিখতে শিখতে এগিয়ে যান।",
  "feat4_h3": "ভুলগুলো পর্যালোচনা করুন",
  "feat4_p": "শুধু আপনার ভুল উত্তর দেওয়া প্রশ্নগুলোর জন্য আলাদা মোড — আপনার দুর্বলতা দক্ষতার সাথে কাটান।",
  "feat5_h3": "প্রিয়",
  "feat5_p": "কঠিন প্রশ্নগুলো তারকা চিহ্নিত করুন এবং যখন খুশি ফিরে আসুন।",
  "feat6_h3": "সম্পূর্ণ অফলাইন",
  "feat6_p": "মেট্রোতে, লাইনে দাঁড়িয়ে, যেকোনো জায়গায় পড়ুন — কোনো ইন্টারনেট লাগবে না।",
  "scr_h2": "অ্যাপটি দেখতে কেমন",
  "scr_lede": "ইন্টারফেস বাংলায়। শান্ত, হালকা ডিজাইন, বাড়তি কিছু নেই।",
  "scr1_alt": "বাংলায় অনূদিত উত্তরসহ প্রশ্নের স্ক্রিন",
  "scr1_cap": "অনুবাদসহ প্রশ্ন ও উত্তর",
  "scr2_alt": "ছবিসহ প্রশ্ন: বুন্ডেসটাগের অধিবেশন কক্ষ",
  "scr2_cap": "ছবিযুক্ত প্রশ্ন — ঠিক পরীক্ষার মতো",
  "scr3_alt": "৬০ মিনিটের টাইমারসহ অনুশীলন পরীক্ষা",
  "scr3_cap": "টাইমারসহ অনুশীলন পরীক্ষা",
  "how_h2": "আত্মবিশ্বাসের তিন ধাপ",
  "how_lede": "ইনস্টল থেকে পরীক্ষার প্রস্তুতি পর্যন্ত।",
  "step1_h3": "ডাউনলোড ও সেটআপ করুন",
  "step1_p": "বিনামূল্যে ইনস্টল করুন, বাংলা ও আপনার রাজ্য বেছে নিন।",
  "step2_h3": "প্রশ্নগুলো অনুশীলন করুন",
  "step2_p": "অনুবাদসহ প্রশ্ন পড়ুন, কঠিনগুলো তারকা চিহ্নিত করুন এবং ভুলগুলো পর্যালোচনা করুন।",
  "step3_h3": "অনুশীলন পরীক্ষা দিন",
  "step3_p": "পরীক্ষা মোডে নিজেকে যাচাই করুন — তারপর আত্মবিশ্বাস নিয়ে আসল পরীক্ষায় বসুন।",
  "final_h2": "আজই প্রস্তুতি শুরু করুন",
  "final_lede": "বিনামূল্যে। বাংলায়। অফলাইনে চলে।",
  "disc_h2": "গুরুত্বপূর্ণ তথ্য",
  "disc1_h3": "এটি সরকারি অ্যাপ নয়",
  "disc1_p": "এটি একটি ব্যক্তিগত শিক্ষামূলক প্রকল্প, অভিবাসন ও শরণার্থী বিষয়ক ফেডারেল দপ্তরের (BAMF) কোনো অফিসিয়াল অ্যাপ নয়। অ্যাপটি কোনো সরকারি কর্তৃপক্ষের সাথে সম্পর্কিত নয় এবং কোনো অফিসিয়াল প্রতিষ্ঠানের প্রতিনিধিত্ব করে না।",
  "disc2_h3": "প্রশ্নের উৎস",
  "disc2_p": "পরীক্ষার প্রশ্নগুলো অফিসিয়াল BAMF প্রশ্ন তালিকার উপর ভিত্তি করে তৈরি। মূল বিষয়বস্তু জার্মান ভাষায় <a href=\"https://www.bamf.de/DE/Themen/Integration/ZugewanderteTeilnehmende/OnlineTestcenter/online-testcenter-node.html\" rel=\"noopener\">BAMF অনলাইন টেস্ট সেন্টারে</a> প্রকাশিত।",
  "disc3_h3": "অনুবাদ সম্পর্কে",
  "disc3_p": "যাদের জার্মান ভাষায় সীমিত জ্ঞান আছে তাদের সহায়তার জন্য অনুবাদগুলো AI দ্বারা তৈরি এবং এতে ভুল থাকতে পারে। কোনো অনুবাদ উন্নত করা উচিত মনে করলে, আপনি অ্যাপ থেকে সরাসরি ডেভেলপারকে জানাতে পারেন। শুধুমাত্র প্রশ্নের মূল জার্মান টেক্সটই নির্ভরযোগ্য।",
  "disc4_h3": "দায়বদ্ধতা অস্বীকার",
  "disc4_p": "এই অ্যাপের বিষয়বস্তু শুধুমাত্র পরীক্ষার প্রস্তুতির জন্য। যত্নসহকারে তৈরি করা সত্ত্বেও, আমরা তথ্যের নির্ভুলতা, সম্পূর্ণতা বা সময়োপযোগিতার নিশ্চয়তা দিই না; এই অ্যাপ ব্যবহারের ফলে সৃষ্ট প্রত্যক্ষ বা পরোক্ষ ক্ষতির জন্য কোনো দায় বাদ দেওয়া হয়েছে। শুধুমাত্র অফিসিয়াল BAMF উপকরণই নির্ভরযোগ্য।",
  "f_brand": "Leben in DE · Trainer",
  "f_about": "মাতৃভাষায় \"Leben in Deutschland\" পরীক্ষার (Einbürgerungstest) প্রস্তুতি। 85apps-এর একটি অ্যাপ।",
  "f_nav_label": "অন্যান্য ভাষা",
  "f_langs_title": "এই পৃষ্ঠাটি অন্যান্য ভাষায়",
  "lang_search": "ভাষা খুঁজুন"
}
